PyDicomGrouping/CTImage.py
PyDicomGrouping/MRImage.py
PyDicomGrouping/__init__.py
PyDicomGrouping/main.py
PyDicomGrouping/utils.py
PyDicomGrouping/dicom_standard_scrapping/DicomStandardEnums.py
PyDicomGrouping/dicom_standard_scrapping/__init__.py
PyDicomGrouping/dicom_standard_scrapping/tree_node_encryptor.py
PyDicomGrouping/dicom_standard_scrapping/webscraping.py
PyDicomGrouping/dicom_standard_scrapping/DicomStandardTreeNodeCaches/12-LeadECG.xz
PyDicomGrouping/dicom_standard_scrapping/DicomStandardTreeNodeCaches/AcquisitionContextSR.xz
PyDicomGrouping/dicom_standard_scrapping/DicomStandardTreeNodeCaches/AdvancedBlendingPresentationState.xz
PyDicomGrouping/dicom_standard_scrapping/DicomStandardTreeNodeCaches/AmbulatoryECG.xz
PyDicomGrouping/dicom_standard_scrapping/DicomStandardTreeNodeCaches/ArterialPulseWaveform.xz
PyDicomGrouping/dicom_standard_scrapping/DicomStandardTreeNodeCaches/AutorefractionMeasurements.xz
PyDicomGrouping/dicom_standard_scrapping/DicomStandardTreeNodeCaches/BasicCardiacElectrophysiologyWaveform.xz
PyDicomGrouping/dicom_standard_scrapping/DicomStandardTreeNodeCaches/BasicDirectory.xz
PyDicomGrouping/dicom_standard_scrapping/DicomStandardTreeNodeCaches/BasicStructuredDisplay.xz
PyDicomGrouping/dicom_standard_scrapping/DicomStandardTreeNodeCaches/BasicTextSR.xz
PyDicomGrouping/dicom_standard_scrapping/DicomStandardTreeNodeCaches/BasicVoiceAudioWaveform.xz
PyDicomGrouping/dicom_standard_scrapping/DicomStandardTreeNodeCaches/BlendingSoftcopyPresentationState.xz
PyDicomGrouping/dicom_standard_scrapping/DicomStandardTreeNodeCaches/BodyPositionWaveform.xz
PyDicomGrouping/dicom_standard_scrapping/DicomStandardTreeNodeCaches/BreastProjectionX-RayImage.xz
PyDicomGrouping/dicom_standard_scrapping/DicomStandardTreeNodeCaches/BreastTomosynthesisImage.xz
PyDicomGrouping/dicom_standard_scrapping/DicomStandardTreeNodeCaches/C-ArmPhoton-ElectronRadiation.xz
PyDicomGrouping_Mac-0.1.33.dist-info/METADATA
PyDicomGrouping_Mac-0.1.33.dist-info/WHEEL
PyDicomGrouping_Mac-0.1.33.dist-info/top_level.txt
PyDicomGrouping_Mac-0.1.33.dist-info/RECORD
